orcid/__init__.py
orcid/orcid.py
orcid-1.0.2.dist-info/METADATA
orcid-1.0.2.dist-info/RECORD
orcid-1.0.2.dist-info/WHEEL
orcid-1.0.2.dist-info/top_level.txt
