Metadata-Version: 2.1
Name: orcid
Version: 1.0.2
Summary: A python wrapper over the ORCID API
Home-page: https://github.com/ORCID/python-orcid
Author: Mateusz Susik
Author-email: mateuszsusik@protonmail.ch
License: BSD
Keywords: orcid,api,wrapper
Platform: UNKNOWN
Classifier: Development Status :: 4 - Beta
Classifier: Intended Audience :: Developers
Classifier: Intended Audience :: Science/Research
Classifier: License :: OSI Approved :: BSD License
Classifier: Operating System :: OS Independent
Classifier: Programming Language :: Python
Classifier: Programming Language :: Python :: 2
Classifier: Programming Language :: Python :: 2.6
Classifier: Programming Language :: Python :: 2.7
Classifier: Programming Language :: Python :: 3
Classifier: Programming Language :: Python :: 3.3
Classifier: Programming Language :: Python :: 3.4
Classifier: Programming Language :: Python :: 3.5
Classifier: Programming Language :: Python :: 3.6
Classifier: Topic :: Internet
Classifier: Topic :: Utilities
Requires-Dist: html5lib
Requires-Dist: beautifulsoup4
Requires-Dist: requests
Requires-Dist: simplejson
Requires-Dist: lxml
